{
  "recentFiles": [
    {
      "basename": "2024-07-11",
      "path": "dailies/2024-07-11.md"
    },
    {
      "basename": "2024-06-18",
      "path": "dailies/2024-06-18.md"
    },
    {
      "basename": "2024-06-16",
      "path": "dailies/2024-06-16.md"
    },
    {
      "basename": "Salwala22distribIncrmntlMLbigTS",
      "path": "lit/lit_notes/Salwala22distribIncrmntlMLbigTS.md"
    },
    {
      "basename": "Obsidian Sync",
      "path": "Obsidian/Obsidian Sync.md"
    },
    {
      "basename": "Signature Transforms for Time Series",
      "path": "topic/Signature Transforms for Time Series.md"
    },
    {
      "basename": "Loning19unifMLinterfaceTSsktime",
      "path": "lit/lit_notes/Loning19unifMLinterfaceTSsktime.md"
    },
    {
      "basename": "Pattnaik20LightGBMautoRgrsSktime",
      "path": "lit/lit_notes/Pattnaik20LightGBMautoRgrsSktime.md"
    },
    {
      "basename": "2024-07-09",
      "path": "dailies/2024-07-09.md"
    },
    {
      "basename": "Morrill21GenSignatureTSfeatExtract",
      "path": "lit/lit_notes/Morrill21GenSignatureTSfeatExtract.md"
    },
    {
      "basename": "Loning19unifMLinterfaceTSsktime",
      "path": "lit/lit_sources/Loning19unifMLinterfaceTSsktime.pdf"
    },
    {
      "basename": "Falkner18hyperparamBOHB",
      "path": "lit/lit_notes/Falkner18hyperparamBOHB.md"
    },
    {
      "basename": "Falkner18hyperparamBOHB",
      "path": "lit/lit_sources/Falkner18hyperparamBOHB.pdf"
    },
    {
      "basename": "Akiba19OptunaHyperparamOpt",
      "path": "lit/lit_notes/Akiba19OptunaHyperparamOpt.md"
    },
    {
      "basename": "Morrill21GenSignatureTSfeatExtract",
      "path": "lit/lit_sources/Morrill21GenSignatureTSfeatExtract.pdf"
    },
    {
      "basename": "Buhler20aatadrivenMktSimSigTransfrm",
      "path": "lit/lit_notes/Buhler20aatadrivenMktSimSigTransfrm.md"
    },
    {
      "basename": "Concept Drift and Adaptation",
      "path": "topic/Concept Drift and Adaptation.md"
    },
    {
      "basename": "Algorithms for AEMO",
      "path": "work/priceFrcstAEMO/Algorithms for AEMO.md"
    },
    {
      "basename": "Akyildirim22sigMethodsMktAnmly",
      "path": "lit/lit_notes/Akyildirim22sigMethodsMktAnmly.md"
    },
    {
      "basename": "Algorithm Plan",
      "path": "work/Research Group Org/Algorithm Plan.md"
    },
    {
      "basename": "Sidogi23SigTransfrmStockLOB",
      "path": "lit/lit_notes/Sidogi23SigTransfrmStockLOB.md"
    },
    {
      "basename": "Sidogi23SignatureTransformLimit.pdf",
      "path": "lit/lit_notes/Sidogi23SignatureTransformLimit.pdf.md"
    },
    {
      "basename": "Salwala22distribIncrmntlMLbigTS",
      "path": "lit/lit_sources/Salwala22distribIncrmntlMLbigTS.pdf"
    },
    {
      "basename": "2024-04-17",
      "path": "dailies/2024-04-17.md"
    },
    {
      "basename": "Current Obsidian Commands and Hotkeys",
      "path": "Obsidian/Current Obsidian Commands and Hotkeys.md"
    },
    {
      "basename": "Default Obsidian Editing Hotkeys",
      "path": "Obsidian/Default Obsidian Editing Hotkeys.md"
    },
    {
      "basename": "TODO Obsidian",
      "path": "Obsidian/TODO Obsidian.md"
    },
    {
      "basename": "Installed plugins",
      "path": "Obsidian/Installed plugins.md"
    },
    {
      "basename": "tmp_tst 2",
      "path": "test/tmp_tst 2.md"
    },
    {
      "basename": "Untitled",
      "path": "test/Untitled.md"
    },
    {
      "basename": "tmp tst 1",
      "path": "test/tmp tst 1.md"
    },
    {
      "basename": "Géron-Hands-On Machine Learning with Scikit-Learn and TensorFlow",
      "path": "Kindle/Géron-Hands-On Machine Learning with Scikit-Learn and TensorFlow.md"
    },
    {
      "basename": "Ahrens-How to Take Smart Notes",
      "path": "Kindle/Ahrens-How to Take Smart Notes.md"
    },
    {
      "basename": "2024-07-06",
      "path": "dailies/2024-07-06.md"
    },
    {
      "basename": "Contextual Optimization",
      "path": "topic/Contextual Optimization.md"
    },
    {
      "basename": "2024-03-24",
      "path": "dailies/2024-03-24.md"
    },
    {
      "basename": "2024-04-08",
      "path": "dailies/2024-04-08.md"
    },
    {
      "basename": "2023-08-19",
      "path": "dailies/2023-08-19.md"
    },
    {
      "basename": "2024-03-23",
      "path": "dailies/2024-03-23.md"
    },
    {
      "basename": "2024-03-09",
      "path": "dailies/2024-03-09.md"
    },
    {
      "basename": "Outliner Plugin ORIG",
      "path": "dailies/Outliner Plugin ORIG.md"
    },
    {
      "basename": "AEMO24vulnerableTransmissionList",
      "path": "lit/lit_notes/AEMO24vulnerableTransmissionList.md"
    },
    {
      "basename": "2024-06-19",
      "path": "dailies/2024-06-19.md"
    },
    {
      "basename": "2024-04-03",
      "path": "dailies/2024-04-03.md"
    },
    {
      "basename": "Optimization for Energy Markets",
      "path": "topic/Optimization for Energy Markets.md"
    },
    {
      "basename": "2024-07-04",
      "path": "dailies/2024-07-04.md"
    },
    {
      "basename": "Lainder22frcstGBTaugTuneCV",
      "path": "lit/lit_notes/Lainder22frcstGBTaugTuneCV.md"
    },
    {
      "basename": "Schreiber21TaskEmbeddingTemporal",
      "path": "lit/lit_notes/Schreiber21TaskEmbeddingTemporal.md"
    },
    {
      "basename": "LightGBM",
      "path": "topic/LightGBM.md"
    },
    {
      "basename": "Tan24llmUseTSfrcst",
      "path": "lit/lit_notes/Tan24llmUseTSfrcst.md"
    }
  ],
  "omittedPaths": [],
  "maxLength": null,
  "openType": "tab"
}